{
  "author": {
    "id": "author:nava-yuwa-central",
    "name": "Nava Yuwa Central",
    "slug": "nava-yuwa-central"
  },
  "change_description": "Initial sourcing from MoF DFMIS API",
  "created_at": "2025-12-23T19:11:13.810439Z",
  "entity_or_relationship_id": "entity:project/development_project/dfmis-1187",
  "snapshot": {
    "attributes": null,
    "attributions": [
      {
        "details": {
          "en": {
            "provenance": "human",
            "value": "Imported from DFMIS on 2025-01-26"
          },
          "ne": null
        },
        "title": {
          "en": {
            "provenance": "human",
            "value": "DFMIS"
          },
          "ne": null
        }
      }
    ],
    "contacts": null,
    "created_at": "2025-12-23T19:11:13.810442Z",
    "dates": [
      {
        "date": "2009-02-01",
        "source": "MoF DFMIS",
        "type": "APPROVAL"
      },
      {
        "date": "2014-12-31",
        "source": "MoF DFMIS",
        "type": "COMPLETION"
      }
    ],
    "description": {
      "en": {
        "provenance": "imported",
        "value": "National Education Equity Strategy developed to facilitate greater gender and social equity (e.g. gender, children with disabilities, geographically/ socio-economically disadvantaged children, children living with HIV or affected by AIDS etc.)\r\n\r\nEvidence-based research related to gender and social equity used  in education policies and strategies\r\n\r\nSC100138 – Finnish Fund\r\n\r\nSC109901 – Thematic Fund\r\n\r\nSC110394 – German Fund"
      },
      "ne": null
    },
    "donor_extensions": [
      {
        "donor": "United Nations Children's Fund",
        "donor_project_id": "1187",
        "raw_payload": {
          "id": 3073,
          "organization__development_cooperation_group__architecture__id": 1,
          "organization__development_cooperation_group__architecture__name": "Multilateral Partners",
          "organization__development_cooperation_group__id": 46,
          "organization__development_cooperation_group__name": "United Nations",
          "organization__logo": "",
          "organization__name": "United Nations Children's Fund",
          "organization_id": 11,
          "percentage": 100
        }
      }
    ],
    "executing_agency": "Ministry of Education, Science and Technology",
    "financing": [
      {
        "amount": 666000.0,
        "assistance_type": "technical_assistance",
        "budget_type": "on_budget",
        "currency": "United States Dollar",
        "donor": "United Nations Children's Fund",
        "donor_id": null,
        "financing_instrument": "Sector Wide Approach",
        "is_actual": true,
        "source": "DFMIS",
        "terms": null,
        "transaction_date": "2011-06-01",
        "transaction_type": "commitment"
      },
      {
        "amount": 1000000.0,
        "assistance_type": "grant",
        "budget_type": "on_budget",
        "currency": "United States Dollar",
        "donor": "United Nations Children's Fund",
        "donor_id": null,
        "financing_instrument": "Sector Wide Approach",
        "is_actual": true,
        "source": "DFMIS",
        "terms": null,
        "transaction_date": "2011-06-01",
        "transaction_type": "commitment"
      }
    ],
    "id": "entity:project/development_project/dfmis-1187",
    "identifiers": [
      {
        "name": {
          "en": {
            "provenance": "human",
            "value": "DFMIS Project ID"
          },
          "ne": null
        },
        "scheme": "other",
        "url": "https://dfims.mof.gov.np/projects/1187",
        "value": "1187"
      }
    ],
    "implementing_agency": "Center for Education and Human Resource Development",
    "misspelled_names": null,
    "names": [
      {
        "en": {
          "family": null,
          "full": "Policy and Legislations",
          "given": null,
          "middle": null,
          "prefix": null,
          "suffix": null
        },
        "kind": "PRIMARY",
        "ne": null
      }
    ],
    "pictures": null,
    "project_url": "https://dfims.mof.gov.np/projects/1187",
    "sectors": [
      {
        "donor": null,
        "donor_sector": "Education – Not Elsewhere Classified",
        "donor_subsector": null,
        "normalized_sector": "Education – Not Elsewhere Classified",
        "percentage": null
      }
    ],
    "short_description": null,
    "slug": "dfmis-1187",
    "stage": "completed",
    "sub_type": "development_project",
    "tags": null,
    "total_commitment": 1666000.0,
    "total_disbursement": 398130.0,
    "type": "project",
    "version_summary": {
      "author": {
        "id": "author:nava-yuwa-central",
        "name": "Nava Yuwa Central",
        "slug": "nava-yuwa-central"
      },
      "change_description": "Initial sourcing from MoF DFMIS API",
      "created_at": "2025-12-23T19:11:13.810439Z",
      "entity_or_relationship_id": "entity:project/development_project/dfmis-1187",
      "id": "version:entity:project/development_project/dfmis-1187:1",
      "type": "ENTITY",
      "version_number": 1
    }
  },
  "type": "ENTITY",
  "version_number": 1
}