{
  "author": {
    "id": "author:nava-yuwa-central",
    "name": "Nava Yuwa Central",
    "slug": "nava-yuwa-central"
  },
  "change_description": "Initial sourcing from MoF DFMIS API",
  "created_at": "2025-12-23T19:11:19.423787Z",
  "entity_or_relationship_id": "entity:project/development_project/dfmis-3241",
  "snapshot": {
    "attributes": null,
    "attributions": [
      {
        "details": {
          "en": {
            "provenance": "human",
            "value": "Imported from DFMIS on 2025-01-26"
          },
          "ne": null
        },
        "title": {
          "en": {
            "provenance": "human",
            "value": "DFMIS"
          },
          "ne": null
        }
      }
    ],
    "contacts": null,
    "created_at": "2025-12-23T19:11:19.423795Z",
    "dates": [
      {
        "date": "2018-05-24",
        "source": "MoF DFMIS",
        "type": "APPROVAL"
      },
      {
        "date": "2018-01-01",
        "source": "MoF DFMIS",
        "type": "START"
      },
      {
        "date": "2020-06-30",
        "source": "MoF DFMIS",
        "type": "COMPLETION"
      }
    ],
    "description": null,
    "donor_extensions": [
      {
        "donor": "United Nations Children's Fund",
        "donor_project_id": "3241",
        "raw_payload": {
          "id": 40066,
          "organization__development_cooperation_group__architecture__id": 1,
          "organization__development_cooperation_group__architecture__name": "Multilateral Partners",
          "organization__development_cooperation_group__id": 46,
          "organization__development_cooperation_group__name": "United Nations",
          "organization__logo": "",
          "organization__name": "United Nations Children's Fund",
          "organization_id": 11,
          "percentage": 0
        }
      }
    ],
    "executing_agency": "Ministry of Health and Population",
    "financing": [
      {
        "amount": 148114.0,
        "assistance_type": "other",
        "budget_type": "off_budget",
        "currency": "United States Dollar",
        "donor": "United Nations Children's Fund",
        "donor_id": null,
        "financing_instrument": "Program-Based Support",
        "is_actual": true,
        "source": "DFMIS",
        "terms": null,
        "transaction_date": "2021-06-30",
        "transaction_type": "commitment"
      },
      {
        "amount": 78718.0,
        "assistance_type": "other",
        "budget_type": "off_budget",
        "currency": "United States Dollar",
        "donor": "United Nations Children's Fund",
        "donor_id": null,
        "financing_instrument": "Program-Based Support",
        "is_actual": true,
        "source": "DFMIS",
        "terms": null,
        "transaction_date": "2022-06-30",
        "transaction_type": "commitment"
      },
      {
        "amount": 35355.0,
        "assistance_type": "technical_assistance",
        "budget_type": "off_budget",
        "currency": "United States Dollar",
        "donor": "United Nations Children's Fund",
        "donor_id": null,
        "financing_instrument": "Program-Based Support",
        "is_actual": true,
        "source": "DFMIS",
        "terms": null,
        "transaction_date": "2021-06-30",
        "transaction_type": "commitment"
      },
      {
        "amount": 24479.0,
        "assistance_type": "technical_assistance",
        "budget_type": "off_budget",
        "currency": "United States Dollar",
        "donor": "United Nations Children's Fund",
        "donor_id": null,
        "financing_instrument": "Program-Based Support",
        "is_actual": true,
        "source": "DFMIS",
        "terms": null,
        "transaction_date": "2022-06-30",
        "transaction_type": "commitment"
      },
      {
        "amount": 4412.0,
        "assistance_type": "technical_assistance",
        "budget_type": "off_budget",
        "currency": "United States Dollar",
        "donor": "United Nations Children's Fund",
        "donor_id": null,
        "financing_instrument": "Program-Based Support",
        "is_actual": true,
        "source": "DFMIS",
        "terms": null,
        "transaction_date": "2023-02-01",
        "transaction_type": "commitment"
      },
      {
        "amount": 39545.0,
        "assistance_type": "technical_assistance",
        "budget_type": "off_budget",
        "currency": "United States Dollar",
        "donor": "United Nations Children's Fund",
        "donor_id": null,
        "financing_instrument": "Humanitarian Assistance",
        "is_actual": true,
        "source": "DFMIS",
        "terms": null,
        "transaction_date": "2020-03-30",
        "transaction_type": "commitment"
      },
      {
        "amount": 370036.0,
        "assistance_type": "technical_assistance",
        "budget_type": "off_budget",
        "currency": "United States Dollar",
        "donor": "United Nations Children's Fund",
        "donor_id": null,
        "financing_instrument": "Humanitarian Assistance",
        "is_actual": true,
        "source": "DFMIS",
        "terms": null,
        "transaction_date": "2021-06-30",
        "transaction_type": "commitment"
      },
      {
        "amount": 227971.0,
        "assistance_type": "technical_assistance",
        "budget_type": "off_budget",
        "currency": "United States Dollar",
        "donor": "United Nations Children's Fund",
        "donor_id": null,
        "financing_instrument": "Humanitarian Assistance",
        "is_actual": true,
        "source": "DFMIS",
        "terms": null,
        "transaction_date": "2022-06-30",
        "transaction_type": "commitment"
      },
      {
        "amount": 4799245.0,
        "assistance_type": "technical_assistance",
        "budget_type": "off_budget",
        "currency": "United States Dollar",
        "donor": "United Nations Children's Fund",
        "donor_id": null,
        "financing_instrument": "Humanitarian Assistance",
        "is_actual": true,
        "source": "DFMIS",
        "terms": null,
        "transaction_date": "2020-07-31",
        "transaction_type": "commitment"
      },
      {
        "amount": 3655360.0,
        "assistance_type": "technical_assistance",
        "budget_type": "off_budget",
        "currency": "United States Dollar",
        "donor": "United Nations Children's Fund",
        "donor_id": null,
        "financing_instrument": "Humanitarian Assistance",
        "is_actual": true,
        "source": "DFMIS",
        "terms": null,
        "transaction_date": "2021-06-30",
        "transaction_type": "commitment"
      },
      {
        "amount": 3026367.0,
        "assistance_type": "technical_assistance",
        "budget_type": "off_budget",
        "currency": "United States Dollar",
        "donor": "United Nations Children's Fund",
        "donor_id": null,
        "financing_instrument": "Humanitarian Assistance",
        "is_actual": true,
        "source": "DFMIS",
        "terms": null,
        "transaction_date": "2022-06-30",
        "transaction_type": "commitment"
      },
      {
        "amount": 940200.0,
        "assistance_type": "technical_assistance",
        "budget_type": "off_budget",
        "currency": "United States Dollar",
        "donor": "United Nations Children's Fund",
        "donor_id": null,
        "financing_instrument": "Program-Based Support",
        "is_actual": true,
        "source": "DFMIS",
        "terms": null,
        "transaction_date": "2018-01-01",
        "transaction_type": "commitment"
      },
      {
        "amount": 233400.0,
        "assistance_type": "technical_assistance",
        "budget_type": "off_budget",
        "currency": "United States Dollar",
        "donor": "United Nations Children's Fund",
        "donor_id": null,
        "financing_instrument": "Program-Based Support",
        "is_actual": true,
        "source": "DFMIS",
        "terms": null,
        "transaction_date": "2018-01-01",
        "transaction_type": "commitment"
      },
      {
        "amount": 179796.0,
        "assistance_type": "technical_assistance",
        "budget_type": "off_budget",
        "currency": "United States Dollar",
        "donor": "United Nations Children's Fund",
        "donor_id": null,
        "financing_instrument": "Program-Based Support",
        "is_actual": true,
        "source": "DFMIS",
        "terms": null,
        "transaction_date": "2021-06-30",
        "transaction_type": "commitment"
      },
      {
        "amount": 71256.0,
        "assistance_type": "technical_assistance",
        "budget_type": "off_budget",
        "currency": "United States Dollar",
        "donor": "United Nations Children's Fund",
        "donor_id": null,
        "financing_instrument": "Program-Based Support",
        "is_actual": true,
        "source": "DFMIS",
        "terms": null,
        "transaction_date": "2022-06-30",
        "transaction_type": "commitment"
      },
      {
        "amount": 118832.0,
        "assistance_type": "technical_assistance",
        "budget_type": "off_budget",
        "currency": "United States Dollar",
        "donor": "United Nations Children's Fund",
        "donor_id": null,
        "financing_instrument": "Program-Based Support",
        "is_actual": true,
        "source": "DFMIS",
        "terms": null,
        "transaction_date": "2023-02-01",
        "transaction_type": "commitment"
      }
    ],
    "id": "entity:project/development_project/dfmis-3241",
    "identifiers": [
      {
        "name": {
          "en": {
            "provenance": "human",
            "value": "DFMIS Project ID"
          },
          "ne": null
        },
        "scheme": "other",
        "url": "https://dfims.mof.gov.np/projects/3241",
        "value": "3241"
      }
    ],
    "implementing_agency": "Ministry of Health and Population",
    "misspelled_names": null,
    "names": [
      {
        "en": {
          "family": null,
          "full": "1.4 Health Sector Support, DRR and Emergency",
          "given": null,
          "middle": null,
          "prefix": null,
          "suffix": null
        },
        "kind": "PRIMARY",
        "ne": null
      }
    ],
    "pictures": null,
    "project_url": "https://dfims.mof.gov.np/projects/3241",
    "sectors": [
      {
        "donor": null,
        "donor_sector": "Health – Not Elsewhere classified",
        "donor_subsector": null,
        "normalized_sector": "Health – Not Elsewhere classified",
        "percentage": null
      }
    ],
    "short_description": null,
    "slug": "dfmis-3241",
    "stage": "completed",
    "sub_type": "development_project",
    "tags": null,
    "total_commitment": 13953086.0,
    "total_disbursement": 10950832.0,
    "type": "project",
    "version_summary": {
      "author": {
        "id": "author:nava-yuwa-central",
        "name": "Nava Yuwa Central",
        "slug": "nava-yuwa-central"
      },
      "change_description": "Initial sourcing from MoF DFMIS API",
      "created_at": "2025-12-23T19:11:19.423787Z",
      "entity_or_relationship_id": "entity:project/development_project/dfmis-3241",
      "id": "version:entity:project/development_project/dfmis-3241:1",
      "type": "ENTITY",
      "version_number": 1
    }
  },
  "type": "ENTITY",
  "version_number": 1
}