{
  "attributes": null,
  "attributions": [
    {
      "details": {
        "en": {
          "provenance": "human",
          "value": "Imported from DFMIS on 2025-01-26"
        },
        "ne": null
      },
      "title": {
        "en": {
          "provenance": "human",
          "value": "DFMIS"
        },
        "ne": null
      }
    }
  ],
  "contacts": null,
  "created_at": "2025-12-23T19:11:23.042222Z",
  "dates": [
    {
      "date": "2024-01-01",
      "source": "MoF DFMIS",
      "type": "APPROVAL"
    },
    {
      "date": "2024-01-01",
      "source": "MoF DFMIS",
      "type": "START"
    },
    {
      "date": "2025-12-31",
      "source": "MoF DFMIS",
      "type": "COMPLETION"
    }
  ],
  "description": {
    "en": {
      "provenance": "imported",
      "value": "Priority one: Inclusive employment, sustainable enterprises and livelihoods, and social securityPriority two: Promotion and application of international labour standards focusing on fundamental principles and rights at workPriority three: Strong tripartite constituents and effective social dialogueEnabling outcome: Increased coherence and integration across DWCP, UNSDCF and the national plans"
    },
    "ne": null
  },
  "donor_extensions": [
    {
      "donor": "International Labour Organization",
      "donor_project_id": "6579",
      "raw_payload": {
        "id": 44000,
        "organization__development_cooperation_group__architecture__id": 1,
        "organization__development_cooperation_group__architecture__name": "Multilateral Partners",
        "organization__development_cooperation_group__id": 46,
        "organization__development_cooperation_group__name": "United Nations",
        "organization__logo": "",
        "organization__name": "International Labour Organization",
        "organization_id": 13,
        "percentage": 0
      }
    }
  ],
  "executing_agency": "Ministry of Labour, Employment and Social Security",
  "financing": [
    {
      "amount": 8000000.0,
      "assistance_type": "other",
      "budget_type": "off_budget",
      "currency": "United States Dollar",
      "donor": "International Labour Organization",
      "donor_id": null,
      "financing_instrument": "Program-Based Support",
      "is_actual": true,
      "source": "DFMIS",
      "terms": null,
      "transaction_date": "2024-01-01",
      "transaction_type": "commitment"
    }
  ],
  "identifiers": [
    {
      "name": {
        "en": {
          "provenance": "human",
          "value": "DFMIS Project ID"
        },
        "ne": null
      },
      "scheme": "other",
      "url": "https://dfims.mof.gov.np/projects/6579",
      "value": "6579"
    }
  ],
  "implementing_agency": "International Labour Organization",
  "misspelled_names": null,
  "names": [
    {
      "en": {
        "family": null,
        "full": "Advancing social justice, promoting decent work",
        "given": null,
        "middle": null,
        "prefix": null,
        "suffix": null
      },
      "kind": "PRIMARY",
      "ne": null
    }
  ],
  "pictures": null,
  "project_url": "https://dfims.mof.gov.np/projects/6579",
  "sectors": [
    {
      "donor": null,
      "donor_sector": "General Economic Commercial and Labor Affairs",
      "donor_subsector": null,
      "normalized_sector": "General Economic Commercial and Labor Affairs",
      "percentage": null
    }
  ],
  "short_description": null,
  "slug": "dfmis-6579",
  "stage": "unknown",
  "sub_type": "development_project",
  "tags": null,
  "total_commitment": 8000000.0,
  "total_disbursement": 6374516.0,
  "type": "project",
  "version_summary": {
    "author": {
      "id": "author:nava-yuwa-central",
      "name": "Nava Yuwa Central",
      "slug": "nava-yuwa-central"
    },
    "change_description": "Initial sourcing from MoF DFMIS API",
    "created_at": "2025-12-23T19:11:23.042219Z",
    "entity_or_relationship_id": "entity:project/development_project/dfmis-6579",
    "type": "ENTITY",
    "version_number": 1
  }
}