{
  "attributes": null,
  "attributions": [
    {
      "details": {
        "en": {
          "provenance": "human",
          "value": "Imported from DFMIS on 2025-01-26"
        },
        "ne": null
      },
      "title": {
        "en": {
          "provenance": "human",
          "value": "DFMIS"
        },
        "ne": null
      }
    }
  ],
  "contacts": null,
  "created_at": "2025-12-23T19:11:06.993476Z",
  "dates": [
    {
      "date": "2010-07-16",
      "source": "MoF DFMIS",
      "type": "APPROVAL"
    },
    {
      "date": "2010-07-16",
      "source": "MoF DFMIS",
      "type": "START"
    },
    {
      "date": "2013-07-15",
      "source": "MoF DFMIS",
      "type": "COMPLETION"
    }
  ],
  "description": {
    "en": {
      "provenance": "imported",
      "value": "To provide international protection and assistance to refugees, asylum seekers and people without citizenship in Nepal."
    },
    "ne": null
  },
  "donor_extensions": [
    {
      "donor": "United Nations High Commissioner for Refugees",
      "donor_project_id": "33",
      "raw_payload": {
        "id": 485,
        "organization__development_cooperation_group__architecture__id": 1,
        "organization__development_cooperation_group__architecture__name": "Multilateral Partners",
        "organization__development_cooperation_group__id": 46,
        "organization__development_cooperation_group__name": "United Nations",
        "organization__logo": "",
        "organization__name": "United Nations High Commissioner for Refugees",
        "organization_id": 358,
        "percentage": 100
      }
    }
  ],
  "executing_agency": "United Nations High Commissioner for Refugees",
  "financing": [
    {
      "amount": 7436935.0,
      "assistance_type": "technical_assistance",
      "budget_type": "off_budget",
      "currency": "United States Dollar",
      "donor": "United Nations High Commissioner for Refugees",
      "donor_id": null,
      "financing_instrument": "Project Support",
      "is_actual": true,
      "source": "DFMIS",
      "terms": null,
      "transaction_date": "2010-07-16",
      "transaction_type": "commitment"
    },
    {
      "amount": 7390969.0,
      "assistance_type": "technical_assistance",
      "budget_type": "off_budget",
      "currency": "United States Dollar",
      "donor": "United Nations High Commissioner for Refugees",
      "donor_id": null,
      "financing_instrument": "Project Support",
      "is_actual": true,
      "source": "DFMIS",
      "terms": null,
      "transaction_date": "2011-07-16",
      "transaction_type": "commitment"
    },
    {
      "amount": 7383293.0,
      "assistance_type": "technical_assistance",
      "budget_type": "off_budget",
      "currency": "United States Dollar",
      "donor": "United Nations High Commissioner for Refugees",
      "donor_id": null,
      "financing_instrument": "Project Support",
      "is_actual": false,
      "source": "DFMIS",
      "terms": null,
      "transaction_date": "2012-07-16",
      "transaction_type": "commitment"
    }
  ],
  "identifiers": [
    {
      "name": {
        "en": {
          "provenance": "human",
          "value": "DFMIS Project ID"
        },
        "ne": null
      },
      "scheme": "other",
      "url": "https://dfims.mof.gov.np/projects/33",
      "value": "33"
    }
  ],
  "implementing_agency": "United Nations High Commissioner for Refugees",
  "misspelled_names": null,
  "names": [
    {
      "en": {
        "family": null,
        "full": "International Protection and Assistance to Refugees, Asylum Seekers and people without citizenship in Nepal",
        "given": null,
        "middle": null,
        "prefix": null,
        "suffix": null
      },
      "kind": "PRIMARY",
      "ne": null
    }
  ],
  "pictures": null,
  "project_url": "https://dfims.mof.gov.np/projects/33",
  "sectors": [
    {
      "donor": null,
      "donor_sector": "Mining, Manufacturing and Construction",
      "donor_subsector": null,
      "normalized_sector": "Mining, Manufacturing and Construction",
      "percentage": null
    }
  ],
  "short_description": null,
  "slug": "dfmis-33",
  "stage": "completed",
  "sub_type": "development_project",
  "tags": null,
  "total_commitment": 22211197.0,
  "total_disbursement": 10045160.0,
  "type": "project",
  "version_summary": {
    "author": {
      "id": "author:nava-yuwa-central",
      "name": "Nava Yuwa Central",
      "slug": "nava-yuwa-central"
    },
    "change_description": "Initial sourcing from MoF DFMIS API",
    "created_at": "2025-12-23T19:11:06.993474Z",
    "entity_or_relationship_id": "entity:project/development_project/dfmis-33",
    "type": "ENTITY",
    "version_number": 1
  }
}