{
  "attributes": null,
  "attributions": [
    {
      "details": {
        "en": {
          "provenance": "human",
          "value": "Imported from DFMIS on 2025-01-26"
        },
        "ne": null
      },
      "title": {
        "en": {
          "provenance": "human",
          "value": "DFMIS"
        },
        "ne": null
      }
    }
  ],
  "contacts": null,
  "created_at": "2025-12-23T19:11:17.038611Z",
  "dates": [
    {
      "date": "2016-04-08",
      "source": "MoF DFMIS",
      "type": "APPROVAL"
    }
  ],
  "description": null,
  "donor_extensions": [
    {
      "donor": "Deutsche Welthungerhilfe e.V",
      "donor_project_id": "1826",
      "raw_payload": {
        "id": 9944,
        "organization__development_cooperation_group__architecture__id": 3,
        "organization__development_cooperation_group__architecture__name": "Non-Government Organisation",
        "organization__development_cooperation_group__id": 49,
        "organization__development_cooperation_group__name": "INGO",
        "organization__logo": "",
        "organization__name": "Deutsche Welthungerhilfe e.V",
        "organization_id": 529,
        "percentage": 0
      }
    }
  ],
  "executing_agency": "Deutsche Welthungerhilfe e.V",
  "financing": [
    {
      "amount": 1163554.278,
      "assistance_type": "grant",
      "budget_type": "off_budget",
      "currency": "United States Dollar",
      "donor": "Deutsche Welthungerhilfe e.V",
      "donor_id": null,
      "financing_instrument": "Project Support",
      "is_actual": true,
      "source": "DFMIS",
      "terms": null,
      "transaction_date": "2016-04-08",
      "transaction_type": "commitment"
    }
  ],
  "identifiers": [
    {
      "name": {
        "en": {
          "provenance": "human",
          "value": "DFMIS Project ID"
        },
        "ne": null
      },
      "scheme": "other",
      "url": "https://dfims.mof.gov.np/projects/1826",
      "value": "1826"
    }
  ],
  "implementing_agency": "Non Governmental Organisations",
  "misspelled_names": null,
  "names": [
    {
      "en": {
        "family": null,
        "full": "Post Earthquake school reconstruction and rehabilitation program in Dhading and Ramechhap districts of Nepal",
        "given": null,
        "middle": null,
        "prefix": null,
        "suffix": null
      },
      "kind": "PRIMARY",
      "ne": null
    }
  ],
  "pictures": null,
  "project_url": "https://dfims.mof.gov.np/projects/1826",
  "sectors": [
    {
      "donor": null,
      "donor_sector": "Education – Not Elsewhere Classified",
      "donor_subsector": null,
      "normalized_sector": "Education – Not Elsewhere Classified",
      "percentage": null
    }
  ],
  "short_description": null,
  "slug": "dfmis-1826",
  "stage": "completed",
  "sub_type": "development_project",
  "tags": null,
  "total_commitment": 1163554.278,
  "total_disbursement": 117017.244,
  "type": "project",
  "version_summary": {
    "author": {
      "id": "author:nava-yuwa-central",
      "name": "Nava Yuwa Central",
      "slug": "nava-yuwa-central"
    },
    "change_description": "Initial sourcing from MoF DFMIS API",
    "created_at": "2025-12-23T19:11:17.038608Z",
    "entity_or_relationship_id": "entity:project/development_project/dfmis-1826",
    "type": "ENTITY",
    "version_number": 1
  }
}