{
  "author": {
    "id": "author:nava-yuwa-central",
    "name": "Nava Yuwa Central",
    "slug": "nava-yuwa-central"
  },
  "change_description": "Initial sourcing from MoF DFMIS API",
  "created_at": "2025-12-23T19:11:13.794670Z",
  "entity_or_relationship_id": "entity:project/development_project/dfmis-1183",
  "snapshot": {
    "attributes": null,
    "attributions": [
      {
        "details": {
          "en": {
            "provenance": "human",
            "value": "Imported from DFMIS on 2025-01-26"
          },
          "ne": null
        },
        "title": {
          "en": {
            "provenance": "human",
            "value": "DFMIS"
          },
          "ne": null
        }
      }
    ],
    "contacts": null,
    "created_at": "2025-12-23T19:11:13.794673Z",
    "dates": [
      {
        "date": "2016-04-08",
        "source": "MoF DFMIS",
        "type": "APPROVAL"
      }
    ],
    "description": {
      "en": {
        "provenance": "imported",
        "value": "Develop and pilot climate resilient design and implementation guidelines and tools to ensure climate change is integrated within local development planning\r\n\r\n \r\n\r\nAssessing the climate change knowledge context and demand at the local and national level\r\n\r\nProvide technical support to government research agency to prepare climate change research and knowledge management strategy\r\n\r\n \r\n\r\nAnalytical review of climate change funding mechanism focusing at different levels to capture lesson learnt and success stories in LDCs and other developing and developed countries.\r\n\r\n \r\n\r\nProvide technical support to government planning process to prepare strategies and guidance on climate change adaptation for climate sensitive line ministries"
      },
      "ne": null
    },
    "donor_extensions": [
      {
        "donor": "Practical Action Nepal",
        "donor_project_id": "1183",
        "raw_payload": {
          "id": 9838,
          "organization__development_cooperation_group__architecture__id": 3,
          "organization__development_cooperation_group__architecture__name": "Non-Government Organisation",
          "organization__development_cooperation_group__id": 49,
          "organization__development_cooperation_group__name": "INGO",
          "organization__logo": "",
          "organization__name": "Practical Action Nepal",
          "organization_id": 318,
          "percentage": 100
        }
      }
    ],
    "executing_agency": "Ministry of Education, Science and Technology",
    "financing": [
      {
        "amount": 2185259.914,
        "assistance_type": "grant",
        "budget_type": "off_budget",
        "currency": "United States Dollar",
        "donor": "Practical Action Nepal",
        "donor_id": null,
        "financing_instrument": "Project Support",
        "is_actual": true,
        "source": "DFMIS",
        "terms": null,
        "transaction_date": "2016-04-08",
        "transaction_type": "commitment"
      }
    ],
    "id": "entity:project/development_project/dfmis-1183",
    "identifiers": [
      {
        "name": {
          "en": {
            "provenance": "human",
            "value": "DFMIS Project ID"
          },
          "ne": null
        },
        "scheme": "other",
        "url": "https://dfims.mof.gov.np/projects/1183",
        "value": "1183"
      }
    ],
    "implementing_agency": "Ministry of Education, Science and Technology",
    "misspelled_names": null,
    "names": [
      {
        "en": {
          "family": null,
          "full": "Climate Proofing Growth and Development Programme",
          "given": null,
          "middle": null,
          "prefix": null,
          "suffix": null
        },
        "kind": "PRIMARY",
        "ne": null
      }
    ],
    "pictures": null,
    "project_url": "https://dfims.mof.gov.np/projects/1183",
    "sectors": [
      {
        "donor": null,
        "donor_sector": "Environmental Protection – Not Elsewhere Classified",
        "donor_subsector": null,
        "normalized_sector": "Environmental Protection – Not Elsewhere Classified",
        "percentage": null
      }
    ],
    "short_description": null,
    "slug": "dfmis-1183",
    "stage": "completed",
    "sub_type": "development_project",
    "tags": null,
    "total_commitment": 2185259.914,
    "total_disbursement": 763621.6449,
    "type": "project",
    "version_summary": {
      "author": {
        "id": "author:nava-yuwa-central",
        "name": "Nava Yuwa Central",
        "slug": "nava-yuwa-central"
      },
      "change_description": "Initial sourcing from MoF DFMIS API",
      "created_at": "2025-12-23T19:11:13.794670Z",
      "entity_or_relationship_id": "entity:project/development_project/dfmis-1183",
      "id": "version:entity:project/development_project/dfmis-1183:1",
      "type": "ENTITY",
      "version_number": 1
    }
  },
  "type": "ENTITY",
  "version_number": 1
}